{
  "channels": {
    "stable": {
      "@fayz-ai/sdk": "^0.8.3",
      "@fayz-ai/core": "^0.8.3",
      "@fayz-ai/auth": "^0.8.3",
      "@fayz-ai/ui": "^0.8.3",
      "@fayz-ai/saas": "^0.8.3",
      "@fayz-ai/shop": "^0.8.3",
      "@fayz-ai/storefront": "^0.8.3",
      "@fayz-ai/portal": "^0.8.0",
      "@fayz-ai/courses": "^0.8.0",
      "@fayz-ai/db": "^0.8.3",
      "@fayz-ai/plugin-agenda": "^0.8.3",
      "@fayz-ai/plugin-auth": "^0.8.0",
      "@fayz-ai/plugin-automations": "^0.8.0",
      "@fayz-ai/plugin-blog": "^0.8.1",
      "@fayz-ai/plugin-conversations": "^0.8.3",
      "@fayz-ai/plugin-courses": "^0.8.3",
      "@fayz-ai/plugin-crm": "^0.8.3",
      "@fayz-ai/plugin-dashboard": "^0.8.0",
      "@fayz-ai/plugin-financial": "^0.8.3",
      "@fayz-ai/plugin-forms": "^0.8.0",
      "@fayz-ai/plugin-inventory": "^0.8.3",
      "@fayz-ai/plugin-marketing": "^0.8.1",
      "@fayz-ai/plugin-menu": "^0.8.0",
      "@fayz-ai/plugin-orders": "^0.8.0",
      "@fayz-ai/plugin-payments": "^0.8.0",
      "@fayz-ai/plugin-reports": "^0.8.0",
      "@fayz-ai/plugin-reputation": "^0.8.0",
      "@fayz-ai/plugin-shop": "^0.8.3",
      "@fayz-ai/plugin-sites": "^0.8.0",
      "@fayz-ai/plugin-tables": "^0.8.0",
      "@fayz-ai/plugin-tasks": "^0.8.3"
    },
    "latest": {
      "@fayz-ai/sdk": "^0.8.3",
      "@fayz-ai/core": "^0.8.3",
      "@fayz-ai/auth": "^0.8.3",
      "@fayz-ai/ui": "^0.8.3",
      "@fayz-ai/saas": "^0.8.3",
      "@fayz-ai/shop": "^0.8.3",
      "@fayz-ai/storefront": "^0.8.3",
      "@fayz-ai/portal": "^0.8.0",
      "@fayz-ai/courses": "^0.8.0",
      "@fayz-ai/db": "^0.8.3",
      "@fayz-ai/plugin-agenda": "^0.8.3",
      "@fayz-ai/plugin-auth": "^0.8.0",
      "@fayz-ai/plugin-automations": "^0.8.0",
      "@fayz-ai/plugin-blog": "^0.8.1",
      "@fayz-ai/plugin-conversations": "^0.8.3",
      "@fayz-ai/plugin-courses": "^0.8.3",
      "@fayz-ai/plugin-crm": "^0.8.3",
      "@fayz-ai/plugin-dashboard": "^0.8.0",
      "@fayz-ai/plugin-financial": "^0.8.3",
      "@fayz-ai/plugin-forms": "^0.8.0",
      "@fayz-ai/plugin-inventory": "^0.8.3",
      "@fayz-ai/plugin-marketing": "^0.8.1",
      "@fayz-ai/plugin-menu": "^0.8.0",
      "@fayz-ai/plugin-orders": "^0.8.0",
      "@fayz-ai/plugin-payments": "^0.8.0",
      "@fayz-ai/plugin-reports": "^0.8.0",
      "@fayz-ai/plugin-reputation": "^0.8.0",
      "@fayz-ai/plugin-shop": "^0.8.3",
      "@fayz-ai/plugin-sites": "^0.8.0",
      "@fayz-ai/plugin-tables": "^0.8.0",
      "@fayz-ai/plugin-tasks": "^0.8.3"
    },
    "preview": {
      "@fayz-ai/sdk": "^0.8.3",
      "@fayz-ai/core": "^0.8.3",
      "@fayz-ai/auth": "^0.8.3",
      "@fayz-ai/ui": "^0.8.3",
      "@fayz-ai/saas": "^0.8.3",
      "@fayz-ai/shop": "^0.8.3",
      "@fayz-ai/storefront": "^0.8.3",
      "@fayz-ai/portal": "^0.8.0",
      "@fayz-ai/courses": "^0.8.0",
      "@fayz-ai/db": "^0.8.3",
      "@fayz-ai/plugin-agenda": "^0.8.3",
      "@fayz-ai/plugin-auth": "^0.8.0",
      "@fayz-ai/plugin-automations": "^0.8.0",
      "@fayz-ai/plugin-blog": "^0.8.1",
      "@fayz-ai/plugin-conversations": "^0.8.3",
      "@fayz-ai/plugin-courses": "^0.8.3",
      "@fayz-ai/plugin-crm": "^0.8.3",
      "@fayz-ai/plugin-dashboard": "^0.8.0",
      "@fayz-ai/plugin-financial": "^0.8.3",
      "@fayz-ai/plugin-forms": "^0.8.0",
      "@fayz-ai/plugin-inventory": "^0.8.3",
      "@fayz-ai/plugin-marketing": "^0.8.1",
      "@fayz-ai/plugin-menu": "^0.8.0",
      "@fayz-ai/plugin-orders": "^0.8.0",
      "@fayz-ai/plugin-payments": "^0.8.0",
      "@fayz-ai/plugin-reports": "^0.8.0",
      "@fayz-ai/plugin-reputation": "^0.8.0",
      "@fayz-ai/plugin-shop": "^0.8.3",
      "@fayz-ai/plugin-sites": "^0.8.0",
      "@fayz-ai/plugin-tables": "^0.8.0",
      "@fayz-ai/plugin-tasks": "^0.8.3"
    }
  }
}
